[
  {
    "threadID": "7238141572913472",
    "data": [
      {
        "name": "Singu　Hạnh　Phúc　Có　Thể　Bỏ　Rơi Anh　Mà　Đi　Thật　Xa",
        "id": "100074293234284",
        "exp": 1
      },
      {
        "name": "ta quoc khanh 🌧️",
        "id": "100061286620059",
        "exp": 18
      },
      {
        "name": "AoiPopy　Cần　Gì　Phải　Giả　Vờ Anh　Đâu　Càn　Em　Nữa　HaHa",
        "id": "100091250266334",
        "exp": 68
      },
      {
        "name": "Mohamed Mohamed",
        "id": "61556018798144",
        "exp": 0
      }
    ]
  },
  {
    "threadID": "6889466874434144",
    "data": [
      {
        "name": "AoiPopy　Cần　Gì　Phải　Giả　Vờ Anh　Đâu　Càn　Em　Nữa　HaHa",
        "id": "100091250266334",
        "exp": 2
      },
      {
        "name": "Singu　Hạnh　Phúc　Có　Thể　Bỏ　Rơi Anh　Mà　Đi　Thật　Xa",
        "id": "100074293234284",
        "exp": 0
      },
      {
        "name": "Mohamed Mohamed",
        "id": "61556018798144",
        "exp": 0
      }
    ]
  },
  {
    "threadID": "7218473298264964",
    "data": [
      {
        "name": "Bà'z Hoàng'z Hay'z Dỗi'z",
        "id": "61554330901050",
        "exp": 12
      },
      {
        "name": "Singu　Hạnh　Phúc　Có　Thể　Bỏ　Rơi Anh　Mà　Đi　Thật　Xa",
        "id": "100074293234284",
        "exp": 26
      },
      {
        "name": "Thiết Sát Bất Tử",
        "id": "61554037764879",
        "exp": 15
      }
    ]
  },
  {
    "threadID": "7120465421355196",
    "data": [
      {
        "name": "Singu　Hạnh　Phúc　Có　Thể　Bỏ　Rơi Anh　Mà　Đi　Thật　Xa",
        "id": "100074293234284",
        "exp": 106
      },
      {
        "name": "Megumi AI",
        "id": "61557230453242",
        "exp": 0
      },
      {
        "name": "Goats Bot",
        "id": "61556595972830",
        "exp": 0
      },
      {
        "name": "Bao Ngoc",
        "id": "100079693452448",
        "exp": 0
      },
      {
        "name": "Nguyen Ngoc Meo",
        "id": "100091512157320",
        "exp": 1
      },
      {
        "id": "100072060893482",
        "exp": 0
      },
      {
        "id": "100094732514686",
        "exp": 2
      },
      {
        "id": "100094282837960",
        "exp": 21
      },
      {
        "id": "61555725886498",
        "exp": 22
      },
      {
        "id": "61557099849351",
        "exp": 3
      },
      {
        "id": "100091135014358",
        "exp": 1
      },
      {
        "id": "100080925560378",
        "exp": 0
      }
    ]
  },
  {
    "threadID": "7154485244671336",
    "data": [
      {
        "name": "Thiết Sát Bất Tử",
        "id": "61554037764879",
        "exp": 0
      },
      {
        "name": "Megumi AI",
        "id": "61557230453242",
        "exp": 0
      },
      {
        "name": "ʚHoàng Bảo Phúc Brightɞ",
        "id": "100073420670485",
        "exp": 0
      },
      {
        "name": "Bà'z Hoàng'z Hay'z Dỗi'z",
        "id": "61554330901050",
        "exp": 0
      },
      {
        "name": "Goats Bot",
        "id": "61556595972830",
        "exp": 0
      }
    ]
  }
]