[
    {
        "name_one": "Nguyễn Phấn",
        "ID_one": "100033361006313",
        "name_two": "Nguyễn Hải Đăng ꪜ",
        "ID_two": "100033478361032",
        "status": true,
        "data": {
            "days": "09:25:10 18/11/2022",
            "countDays": 446,
            "point": 999999999999,
            "daily": null,
            "timestamp": 1668738310406
        }
    },
    {
        "name_one": "Ng Kiều Trinh",
        "ID_one": "100079097131835",
        "name_two": "Câụ Chủ Nhỏ",
        "ID_two": "100075885595966",
        "status": true,
        "data": {
            "days": "07:40:44 10/06/2023",
            "countDays": 242,
            "point": 280000,
            "daily": null,
            "timestamp": 1686400844491
        }
    },
    {
        "name_one": "Nguyễn Hiệu",
        "ID_one": "100064671905833",
        "name_two": "Trần Diệu Quang",
        "ID_two": "100065469883699",
        "status": true,
        "data": {
            "days": "08:14:48 10/06/2023",
            "countDays": 242,
            "point": 0,
            "daily": null,
            "timestamp": 1686402888228
        }
    },
    {
        "name_one": "Thúy Thúy",
        "ID_one": "100046224735720",
        "name_two": "Yến Nhi",
        "ID_two": "100068166364490",
        "status": true,
        "data": {
            "days": "10:11:44 11/06/2023",
            "countDays": 241,
            "point": 0,
            "daily": null,
            "timestamp": 1686496304634
        }
    }
]