{
    "total": [
        {
            "id": "100011026299795",
            "count": 0
        },
        {
            "id": "100026715789225",
            "count": 0
        },
        {
            "id": "100055464062036",
            "count": 0
        },
        {
            "id": "100067746274110",
            "count": 0
        },
        {
            "id": "100069403975090",
            "count": 0
        },
        {
            "id": "100075863781789",
            "count": 184
        },
        {
            "id": "100075885595966",
            "count": 4
        },
        {
            "id": "100075955784352",
            "count": 0
        },
        {
            "id": "100075971388119",
            "count": 0
        },
        {
            "id": "100077529039506",
            "count": 0
        },
        {
            "id": "100079978868983",
            "count": 0
        },
        {
            "id": "100084794796348",
            "count": 146
        }
    ],
    "week": [
        {
            "id": "100011026299795",
            "count": 0,
            "name": "Nhật Vy"
        },
        {
            "id": "100026715789225",
            "count": 0,
            "name": "Người dùng facebook"
        },
        {
            "id": "100055464062036",
            "count": 0,
            "name": "Người dùng facebook"
        },
        {
            "id": "100067746274110",
            "count": 0,
            "name": "Người dùng facebook"
        },
        {
            "id": "100069403975090",
            "count": 0,
            "name": "Người dùng facebook"
        },
        {
            "id": "100075863781789",
            "count": 0,
            "name": "Ngọc Nguyên"
        },
        {
            "id": "100075885595966",
            "count": 0,
            "name": "Câụ Chủ Nhỏ"
        },
        {
            "id": "100075955784352",
            "count": 0,
            "name": "Người dùng facebook"
        },
        {
            "id": "100075971388119",
            "count": 0,
            "name": "Người dùng facebook"
        },
        {
            "id": "100077529039506",
            "count": 0,
            "name": "Người dùng facebook"
        },
        {
            "id": "100079978868983",
            "count": 0,
            "name": "Người dùng facebook"
        },
        {
            "id": "100084794796348",
            "count": 0,
            "name": "Đào Ngọc Nguyên"
        }
    ],
    "day": [
        {
            "id": "100011026299795",
            "count": 0,
            "name": "Nhật Vy"
        },
        {
            "id": "100026715789225",
            "count": 0,
            "name": "Người dùng facebook"
        },
        {
            "id": "100055464062036",
            "count": 0,
            "name": "Người dùng facebook"
        },
        {
            "id": "100067746274110",
            "count": 0,
            "name": "Người dùng facebook"
        },
        {
            "id": "100069403975090",
            "count": 0,
            "name": "Người dùng facebook"
        },
        {
            "id": "100075863781789",
            "count": 0,
            "name": "Ngọc Nguyên"
        },
        {
            "id": "100075885595966",
            "count": 0,
            "name": "Câụ Chủ Nhỏ"
        },
        {
            "id": "100075955784352",
            "count": 0,
            "name": "Người dùng facebook"
        },
        {
            "id": "100075971388119",
            "count": 0,
            "name": "Người dùng facebook"
        },
        {
            "id": "100077529039506",
            "count": 0,
            "name": "Người dùng facebook"
        },
        {
            "id": "100079978868983",
            "count": 0,
            "name": "Người dùng facebook"
        },
        {
            "id": "100084794796348",
            "count": 0,
            "name": "Đào Ngọc Nguyên"
        }
    ],
    "time": 6
}